pinfer/__init__.py
pinfer/io.py
pinfer/infer/__init__.py
pinfer/infer/polytree.py
pinfer/itree/__init__.py
pinfer/itree/initialise.py
pinfer/itree/interact.py
pinfer/itree/interact_original.py
pinfer/itree/label.py
pinfer/itree/label_recursive.py
pinfer/itree/utils.py
pinfer/visualise/__init__.py
pinfer/visualise/colormaps.py
pinfer-0.6.2.dist-info/DESCRIPTION.rst
pinfer-0.6.2.dist-info/METADATA
pinfer-0.6.2.dist-info/RECORD
pinfer-0.6.2.dist-info/WHEEL
pinfer-0.6.2.dist-info/metadata.json
pinfer-0.6.2.dist-info/pbr.json
pinfer-0.6.2.dist-info/top_level.txt
tests/__init__.py
tests/test_itree.py
tests/test_pinfer.py
