Metadata-Version: 2.0
Name: pinfer
Version: 0.6.2
Summary: Inference of ancestral Protein Interaction Networks (PINs).
Home-page: https://github.com/nickfyson/pinfer
Author: Nick Fyson
Author-email: mail@nickfyson.co.uk
License: BSD
Keywords: PPI protein modelling interaction
Platform: UNKNOWN
Classifier: Development Status :: 2 - Pre-Alpha
Classifier: Intended Audience :: Developers
Classifier: License :: OSI Approved :: BSD License
Classifier: Natural Language :: English
Classifier: Programming Language :: Python :: 3.4
Requires-Dist: biopython
Requires-Dist: matplotlib
Requires-Dist: networkx (==1.9.1)
Requires-Dist: numpy
Requires-Dist: pygraphviz
Requires-Dist: seaborn
Requires-Dist: sklearn
